tests/__init__.py
tests/test_yaml_transformer.py
yaml_transformer/__init__.py
yaml_transformer-0.1.1.dist-info/LICENSE
yaml_transformer-0.1.1.dist-info/METADATA
yaml_transformer-0.1.1.dist-info/WHEEL
yaml_transformer-0.1.1.dist-info/top_level.txt
yaml_transformer-0.1.1.dist-info/RECORD
