Metadata-Version: 2.1
Name: yaml-transformer
Version: 0.1.1
Summary: A package for enhancing YAML processing with various features.
Home-page: https://github.com/qzchenwl/yaml-transformer
Author: qzchenwl
Author-email: qzchenwl@gmail.com
Classifier: Programming Language :: Python :: 3
Classifier: License :: OSI Approved :: MIT License
Classifier: Operating System :: OS Independent
License-File: LICENSE
Requires-Dist: PyYAML
Requires-Dist: jq
Requires-Dist: requests
Requires-Dist: jsonpath-ng
Provides-Extra: dev
Requires-Dist: pytest ; extra == 'dev'
